grid_vis/__init__.py
grid_vis/gird_vis.py
grid_vis-0.1.2.dist-info/LICENCE
grid_vis-0.1.2.dist-info/METADATA
grid_vis-0.1.2.dist-info/WHEEL
grid_vis-0.1.2.dist-info/top_level.txt
grid_vis-0.1.2.dist-info/RECORD
